{
  "players": [
    {
      "position": "QB",
      "name": "Andrew Luck",
      "nfl_team": "IND",
      "game_result": "Loss",
      "game_score": "8-38",
      "passing_yards": 353,
      "passing_tds": 1,
      "interceptions": 3,
      "rushing_yards": 17,
      "rushing_tds": 0,
      "receiving_yards": 0,
      "receiving_tds": 0,
      "fumble_tds": 0,
      "two_point_conversions": 1,
      "fumbles_lost": 1,
      "fantasy_points": 13.82,
      "touchdowns": 1,
      "lineup_status": "starter",
      "player_id": "2533031"
    },
    {
      "position": "RB",
      "name": "Matt Forte",
      "nfl_team": "CHI",
      "game_result": "Loss",
      "game_score": "19-21",
      "passing_yards": 0,
      "passing_tds": 0,
      "interceptions": 0,
      "rushing_yards": 33,
      "rushing_tds": 0,
      "receiving_yards": 16,
      "receiving_tds": 0,
      "fumble_tds": 0,
      "two_point_conversions": 0,
      "fumbles_lost": 0,
      "fantasy_points": 4.9,
      "lineup_status": "starter",
      "player_id": "234"
    },
    {
      "position": "RB",
      "name": "DeMarco Murray",
      "nfl_team": "DAL",
      "game_result": "Loss",
      "game_score": "17-49",
      "passing_yards": 0,
      "passing_tds": 0,
      "interceptions": 0,
      "rushing_yards": 89,
      "rushing_tds": 1,
      "receiving_yards": 6,
      "receiving_tds": 0,
      "fumble_tds": 0,
      "two_point_conversions": 0,
      "fumbles_lost": 0,
      "fantasy_points": 15.5,
      "touchdowns": 1,
      "lineup_status": "starter",
      "player_id": "2495207"
    },
    {
      "position": "WR",
      "name": "Calvin Johnson",
      "nfl_team": "DET",
      "game_result": "Win",
      "game_score": "21-19",
      "passing_yards": 0,
      "passing_tds": 0,
      "interceptions": 0,
      "rushing_yards": 0,
      "rushing_tds": 0,
      "receiving_yards": 83,
      "receiving_tds": 2,
      "fumble_tds": 0,
      "two_point_conversions": 0,
      "fumbles_lost": 0,
      "fantasy_points": 20.3,
      "touchdowns": 2,
      "lineup_status": "starter",
      "player_id": "2495647"
    },
    {
      "position": "WR",
      "name": "Vincent Jackson",
      "nfl_team": "TB",
      "game_result": "Win",
      "game_score": "22-19",
      "passing_yards": 0,
      "passing_tds": 0,
      "interceptions": 0,
      "rushing_yards": 0,
      "rushing_tds": 0,
      "receiving_yards": 28,
      "receiving_tds": 0,
      "fumble_tds": 0,
      "two_point_conversions": 0,
      "fumbles_lost": 0,
      "fantasy_points": 2.8,
      "lineup_status": "starter",
      "player_id": "2506400"
    },
    {
      "position": "TE",
      "name": "Martellus Bennett",
      "nfl_team": "CHI",
      "game_result": "Loss",
      "game_score": "19-21",
      "passing_yards": 0,
      "passing_tds": 0,
      "interceptions": 0,
      "rushing_yards": 0,
      "rushing_tds": 0,
      "receiving_yards": 29,
      "receiving_tds": 0,
      "fumble_tds": 0,
      "two_point_conversions": 0,
      "fumbles_lost": 0,
      "fantasy_points": 2.9,
      "lineup_status": "starter",
      "player_id": "1062"
    },
    {
      "position": "WR",
      "name": "Denarius Moore",
      "nfl_team": "LV",
      "game_result": "Loss",
      "game_score": "20-24",
      "passing_yards": 0,
      "passing_tds": 0,
      "interceptions": 0,
      "rushing_yards": 0,
      "rushing_tds": 0,
      "receiving_yards": 45,
      "receiving_tds": 0,
      "fumble_tds": 0,
      "two_point_conversions": 0,
      "fumbles_lost": 0,
      "fantasy_points": 4.5,
      "lineup_status": "starter",
      "player_id": "2495315"
    },
    {
      "position": "QB",
      "name": "Ben Roethlisberger",
      "nfl_team": "PIT",
      "game_result": "Win",
      "game_score": "23-10",
      "passing_yards": 204,
      "passing_tds": 1,
      "interceptions": 1,
      "rushing_yards": 0,
      "rushing_tds": 0,
      "receiving_yards": 0,
      "receiving_tds": 0,
      "fumble_tds": 0,
      "two_point_conversions": 0,
      "fumbles_lost": 0,
      "fantasy_points": 10.16,
      "touchdowns": 1,
      "lineup_status": "starter",
      "player_id": "2506109"
    },
    {
      "position": "RB",
      "name": "Mike Tolbert",
      "nfl_team": "CAR",
      "game_result": "Win",
      "game_score": "10-9",
      "passing_yards": 0,
      "passing_tds": 0,
      "interceptions": 0,
      "rushing_yards": 7,
      "rushing_tds": 0,
      "receiving_yards": 16,
      "receiving_tds": 0,
      "fumble_tds": 0,
      "two_point_conversions": 0,
      "fumbles_lost": 0,
      "fantasy_points": 2.3,
      "lineup_status": "starter",
      "player_id": "2507428"
    },
    {
      "position": "WR",
      "name": "Mike Wallace",
      "nfl_team": "MIA",
      "game_result": "Loss",
      "game_score": "19-22",
      "passing_yards": 0,
      "passing_tds": 0,
      "interceptions": 0,
      "rushing_yards": 0,
      "rushing_tds": 0,
      "receiving_yards": 15,
      "receiving_tds": 0,
      "fumble_tds": 0,
      "two_point_conversions": 0,
      "fumbles_lost": 0,
      "fantasy_points": 1.5,
      "lineup_status": "starter",
      "player_id": "2507763"
    },
    {
      "position": "WR",
      "name": "Michael Floyd",
      "nfl_team": "ARI",
      "game_result": "Win",
      "game_score": "27-24",
      "passing_yards": 0,
      "passing_tds": 0,
      "interceptions": 0,
      "rushing_yards": 0,
      "rushing_tds": 0,
      "receiving_yards": 31,
      "receiving_tds": 0,
      "fumble_tds": 0,
      "two_point_conversions": 0,
      "fumbles_lost": 0,
      "fantasy_points": 3.1,
      "lineup_status": "starter",
      "player_id": "2532841"
    },
    {
      "position": "WR",
      "name": "Marlon Brown",
      "nfl_team": "BAL",
      "game_result": "Win",
      "game_score": "20-17",
      "passing_yards": 0,
      "passing_tds": 0,
      "interceptions": 0,
      "rushing_yards": 0,
      "rushing_tds": 0,
      "receiving_yards": 10,
      "receiving_tds": 0,
      "fumble_tds": 0,
      "two_point_conversions": 0,
      "fumbles_lost": 0,
      "fantasy_points": 1.0,
      "lineup_status": "starter",
      "player_id": "2540005"
    },
    {
      "position": "RB",
      "name": "Joseph Randle",
      "nfl_team": "DAL",
      "game_result": "Loss",
      "game_score": "17-49",
      "passing_yards": 0,
      "passing_tds": 0,
      "interceptions": 0,
      "rushing_yards": 0,
      "rushing_tds": 0,
      "receiving_yards": 0,
      "receiving_tds": 0,
      "fumble_tds": 0,
      "two_point_conversions": 0,
      "fumbles_lost": 0,
      "fantasy_points": 0.0,
      "lineup_status": "starter",
      "player_id": "2540171"
    }
  ],
  "source": "html_scraping"
}