{
  "players": [
    {
      "position": "QB",
      "name": "Cam Newton",
      "nfl_team": "CAR",
      "game_result": "Loss",
      "game_score": "23-30",
      "passing_yards": 432,
      "passing_tds": 1,
      "interceptions": 3,
      "rushing_yards": 53,
      "rushing_tds": 1,
      "receiving_yards": 0,
      "receiving_tds": 0,
      "fumble_tds": 0,
      "two_point_conversions": 0,
      "fumbles_lost": 0,
      "fantasy_points": 26.58,
      "touchdowns": 2,
      "lineup_status": "starter",
      "player_id": "2495455"
    },
    {
      "position": "RB",
      "name": "Ray Rice",
      "nfl_team": "BAL",
      "game_result": "Loss",
      "game_score": "13-26",
      "passing_yards": 0,
      "passing_tds": 0,
      "interceptions": 0,
      "rushing_yards": 43,
      "rushing_tds": 0,
      "receiving_yards": 53,
      "receiving_tds": 1,
      "fumble_tds": 0,
      "two_point_conversions": 0,
      "fumbles_lost": 0,
      "fantasy_points": 15.6,
      "touchdowns": 1,
      "lineup_status": "starter",
      "player_id": "941"
    },
    {
      "position": "RB",
      "name": "Michael Turner",
      "nfl_team": "ATL",
      "game_result": "Win",
      "game_score": "35-31",
      "passing_yards": 0,
      "passing_tds": 0,
      "interceptions": 0,
      "rushing_yards": 114,
      "rushing_tds": 1,
      "receiving_yards": 32,
      "receiving_tds": 0,
      "fumble_tds": 0,
      "two_point_conversions": 0,
      "fumbles_lost": 0,
      "fantasy_points": 20.6,
      "touchdowns": 1,
      "lineup_status": "starter",
      "player_id": "2506014"
    },
    {
      "position": "WR",
      "name": "Steve Johnson",
      "nfl_team": "BUF",
      "game_result": "Win",
      "game_score": "38-35",
      "passing_yards": 0,
      "passing_tds": 0,
      "interceptions": 0,
      "rushing_yards": 0,
      "rushing_tds": 0,
      "receiving_yards": 96,
      "receiving_tds": 1,
      "fumble_tds": 0,
      "two_point_conversions": 0,
      "fumbles_lost": 0,
      "fantasy_points": 15.6,
      "touchdowns": 1,
      "lineup_status": "starter",
      "player_id": "768"
    },
    {
      "position": "WR",
      "name": "Plaxico Burress",
      "nfl_team": "NYJ",
      "game_result": "Win",
      "game_score": "32-3",
      "passing_yards": 0,
      "passing_tds": 0,
      "interceptions": 0,
      "rushing_yards": 0,
      "rushing_tds": 0,
      "receiving_yards": 0,
      "receiving_tds": 0,
      "fumble_tds": 0,
      "two_point_conversions": 0,
      "fumbles_lost": 0,
      "fantasy_points": 0.0,
      "lineup_status": "starter",
      "player_id": "2504253"
    },
    {
      "position": "WR",
      "name": "Jabar Gaffney",
      "nfl_team": "WAS",
      "game_result": "Win",
      "game_score": "22-21",
      "passing_yards": 0,
      "passing_tds": 0,
      "interceptions": 0,
      "rushing_yards": 0,
      "rushing_tds": 0,
      "receiving_yards": 62,
      "receiving_tds": 0,
      "fumble_tds": 0,
      "two_point_conversions": 0,
      "fumbles_lost": 0,
      "fantasy_points": 6.2,
      "lineup_status": "starter",
      "player_id": "2505033"
    },
    {
      "position": "TE",
      "name": "Aaron Hernandez",
      "nfl_team": "NE",
      "game_result": "Win",
      "game_score": "35-21",
      "passing_yards": 0,
      "passing_tds": 0,
      "interceptions": 0,
      "rushing_yards": 0,
      "rushing_tds": 0,
      "receiving_yards": 62,
      "receiving_tds": 1,
      "fumble_tds": 0,
      "two_point_conversions": 0,
      "fumbles_lost": 0,
      "fantasy_points": 12.2,
      "touchdowns": 1,
      "lineup_status": "starter",
      "player_id": "497244"
    },
    {
      "position": "QB",
      "name": "Chad Henne",
      "nfl_team": "MIA",
      "game_result": "Loss",
      "game_score": "13-23",
      "passing_yards": 170,
      "passing_tds": 1,
      "interceptions": 1,
      "rushing_yards": 26,
      "rushing_tds": 0,
      "receiving_yards": 0,
      "receiving_tds": 0,
      "fumble_tds": 0,
      "two_point_conversions": 0,
      "fumbles_lost": 0,
      "fantasy_points": 11.4,
      "touchdowns": 1,
      "lineup_status": "starter",
      "player_id": "252"
    },
    {
      "position": "RB",
      "name": "Ryan Mathews",
      "nfl_team": "LAC",
      "game_result": "Loss",
      "game_score": "21-35",
      "passing_yards": 0,
      "passing_tds": 0,
      "interceptions": 0,
      "rushing_yards": 64,
      "rushing_tds": 1,
      "receiving_yards": 62,
      "receiving_tds": 0,
      "fumble_tds": 0,
      "two_point_conversions": 0,
      "fumbles_lost": 0,
      "fantasy_points": 18.6,
      "touchdowns": 1,
      "lineup_status": "starter",
      "player_id": "497188"
    },
    {
      "position": "WR",
      "name": "Dwayne Bowe",
      "nfl_team": "KC",
      "game_result": "Loss",
      "game_score": "3-48",
      "passing_yards": 0,
      "passing_tds": 0,
      "interceptions": 0,
      "rushing_yards": 12,
      "rushing_tds": 0,
      "receiving_yards": 101,
      "receiving_tds": 0,
      "fumble_tds": 0,
      "two_point_conversions": 0,
      "fumbles_lost": 0,
      "fantasy_points": 11.3,
      "lineup_status": "starter",
      "player_id": "2495558"
    },
    {
      "position": "WR",
      "name": "Steve Breaston",
      "nfl_team": "KC",
      "game_result": "Loss",
      "game_score": "3-48",
      "passing_yards": 0,
      "passing_tds": 0,
      "interceptions": 0,
      "rushing_yards": 0,
      "rushing_tds": 0,
      "receiving_yards": 7,
      "receiving_tds": 0,
      "fumble_tds": 0,
      "two_point_conversions": 0,
      "fumbles_lost": 0,
      "fantasy_points": 0.7,
      "lineup_status": "starter",
      "player_id": "2495562"
    },
    {
      "position": "WR",
      "name": "Chad Ochocinco",
      "nfl_team": "NE",
      "game_result": "Win",
      "game_score": "35-21",
      "passing_yards": 0,
      "passing_tds": 0,
      "interceptions": 0,
      "rushing_yards": 0,
      "rushing_tds": 0,
      "receiving_yards": 45,
      "receiving_tds": 0,
      "fumble_tds": 0,
      "two_point_conversions": 0,
      "fumbles_lost": 0,
      "fantasy_points": 4.5,
      "lineup_status": "starter",
      "player_id": "2504651"
    },
    {
      "position": "QB",
      "name": "Eli Manning",
      "nfl_team": "NYG",
      "game_result": "Win",
      "game_score": "28-16",
      "passing_yards": 223,
      "passing_tds": 2,
      "interceptions": 1,
      "rushing_yards": -12,
      "rushing_tds": 0,
      "receiving_yards": 0,
      "receiving_tds": 0,
      "fumble_tds": 0,
      "two_point_conversions": 0,
      "fumbles_lost": 0,
      "fantasy_points": 13.72,
      "touchdowns": 2,
      "lineup_status": "starter",
      "player_id": "2505996"
    }
  ],
  "source": "html_scraping"
}