{
  "players": [
    {
      "position": "QB",
      "name": "Justin Herbert",
      "nfl_team": "LAC",
      "game_result": "Win",
      "game_score": "47-42",
      "passing_yards": 398,
      "passing_tds": 4,
      "interceptions": 0,
      "rushing_yards": 29,
      "rushing_tds": 1,
      "receiving_yards": 0,
      "receiving_tds": 0,
      "fumble_tds": 0,
      "two_point_conversions": 1,
      "fumbles_lost": 0,
      "fantasy_points": 42.82,
      "touchdowns": 5,
      "lineup_status": "starter",
      "player_id": "2565045"
    },
    {
      "position": "RB",
      "name": "Damien Williams",
      "nfl_team": "ATL",
      "game_result": "Win",
      "game_score": "27-20",
      "passing_yards": 0,
      "passing_tds": 0,
      "interceptions": 0,
      "rushing_yards": 64,
      "rushing_tds": 1,
      "receiving_yards": 20,
      "receiving_tds": 0,
      "fumble_tds": 0,
      "two_point_conversions": 0,
      "fumbles_lost": 0,
      "fantasy_points": 14.4,
      "touchdowns": 1,
      "lineup_status": "starter",
      "player_id": "2550512"
    },
    {
      "position": "RB",
      "name": "Darrell Henderson",
      "nfl_team": "LA",
      "game_result": "Win",
      "game_score": "26-17",
      "passing_yards": 0,
      "passing_tds": 0,
      "interceptions": 0,
      "rushing_yards": 82,
      "rushing_tds": 1,
      "receiving_yards": 17,
      "receiving_tds": 0,
      "fumble_tds": 0,
      "two_point_conversions": 0,
      "fumbles_lost": 0,
      "fantasy_points": 15.9,
      "touchdowns": 1,
      "lineup_status": "starter",
      "player_id": "2562574"
    },
    {
      "position": "WR",
      "name": "DK Metcalf",
      "nfl_team": "SEA",
      "game_result": "Loss",
      "game_score": "17-26",
      "passing_yards": 0,
      "passing_tds": 0,
      "interceptions": 0,
      "rushing_yards": 0,
      "rushing_tds": 0,
      "receiving_yards": 98,
      "receiving_tds": 2,
      "fumble_tds": 0,
      "two_point_conversions": 0,
      "fumbles_lost": 0,
      "fantasy_points": 21.8,
      "touchdowns": 2,
      "lineup_status": "starter",
      "player_id": "2562685"
    },
    {
      "position": "WR",
      "name": "Deebo Samuel",
      "nfl_team": "SF",
      "game_result": "Loss",
      "game_score": "10-17",
      "passing_yards": 0,
      "passing_tds": 0,
      "interceptions": 0,
      "rushing_yards": 13,
      "rushing_tds": 1,
      "receiving_yards": 58,
      "receiving_tds": 0,
      "fumble_tds": 0,
      "two_point_conversions": 0,
      "fumbles_lost": 0,
      "fantasy_points": 13.1,
      "touchdowns": 1,
      "lineup_status": "starter",
      "player_id": "2562721"
    },
    {
      "position": "TE",
      "name": "Mark Andrews",
      "nfl_team": "BAL",
      "game_result": "Win",
      "game_score": "31-25",
      "passing_yards": 0,
      "passing_tds": 0,
      "interceptions": 0,
      "rushing_yards": 0,
      "rushing_tds": 0,
      "receiving_yards": 147,
      "receiving_tds": 2,
      "fumble_tds": 0,
      "two_point_conversions": 2,
      "fumbles_lost": 0,
      "fantasy_points": 30.7,
      "touchdowns": 2,
      "lineup_status": "starter",
      "player_id": "2560957"
    },
    {
      "position": "WR",
      "name": "Mike Williams",
      "nfl_team": "LAC",
      "game_result": "Win",
      "game_score": "47-42",
      "passing_yards": 0,
      "passing_tds": 0,
      "interceptions": 0,
      "rushing_yards": 0,
      "rushing_tds": 0,
      "receiving_yards": 165,
      "receiving_tds": 2,
      "fumble_tds": 0,
      "two_point_conversions": 0,
      "fumbles_lost": 0,
      "fantasy_points": 28.5,
      "touchdowns": 2,
      "lineup_status": "starter",
      "player_id": "2558846"
    },
    {
      "position": "BN",
      "name": "Antonio Brown WR Q",
      "game_result": "Bye",
      "status": "",
      "passing_yards": 0,
      "passing_tds": 0,
      "interceptions": 0,
      "rushing_yards": 0,
      "rushing_tds": 0,
      "receiving_yards": 124,
      "receiving_tds": 2,
      "fumble_tds": 0,
      "two_point_conversions": 0,
      "fumbles_lost": 0,
      "fantasy_points": 24.4,
      "touchdowns": 2,
      "lineup_status": "bench",
      "player_id": "2508061"
    },
    {
      "position": "WR",
      "name": "Odell Beckham Jr.",
      "nfl_team": "LA O",
      "game_result": "Win",
      "game_score": "26-17",
      "passing_yards": 0,
      "passing_tds": 0,
      "interceptions": 0,
      "rushing_yards": 0,
      "rushing_tds": 0,
      "receiving_yards": 20,
      "receiving_tds": 0,
      "fumble_tds": 0,
      "two_point_conversions": 0,
      "fumbles_lost": 0,
      "fantasy_points": 2.0,
      "lineup_status": "starter",
      "player_id": "2543496"
    },
    {
      "position": "RB",
      "name": "Sony Michel",
      "nfl_team": "LA",
      "game_result": "Win",
      "game_score": "26-17",
      "passing_yards": 0,
      "passing_tds": 0,
      "interceptions": 0,
      "rushing_yards": 37,
      "rushing_tds": 1,
      "receiving_yards": 8,
      "receiving_tds": 0,
      "fumble_tds": 0,
      "two_point_conversions": 0,
      "fumbles_lost": 0,
      "fantasy_points": 10.5,
      "touchdowns": 1,
      "lineup_status": "starter",
      "player_id": "2560809"
    },
    {
      "position": "RB",
      "name": "James Conner",
      "nfl_team": "ARI",
      "game_result": "Win",
      "game_score": "17-10",
      "passing_yards": 0,
      "passing_tds": 0,
      "interceptions": 0,
      "rushing_yards": 29,
      "rushing_tds": 1,
      "receiving_yards": 8,
      "receiving_tds": 0,
      "fumble_tds": 0,
      "two_point_conversions": 0,
      "fumbles_lost": 0,
      "fantasy_points": 9.7,
      "touchdowns": 1,
      "lineup_status": "starter",
      "player_id": "2557978"
    },
    {
      "position": "RB",
      "name": "Josh Jacobs",
      "nfl_team": "LV",
      "game_result": "Loss",
      "game_score": "9-20",
      "passing_yards": 0,
      "passing_tds": 0,
      "interceptions": 0,
      "rushing_yards": 48,
      "rushing_tds": 1,
      "receiving_yards": 19,
      "receiving_tds": 0,
      "fumble_tds": 0,
      "two_point_conversions": 0,
      "fumbles_lost": 0,
      "fantasy_points": 12.7,
      "touchdowns": 1,
      "lineup_status": "starter",
      "player_id": "2562377"
    },
    {
      "position": "RB",
      "name": "David Montgomery",
      "nfl_team": "CHI",
      "game_result": "Win",
      "game_score": "20-9",
      "passing_yards": 0,
      "passing_tds": 0,
      "interceptions": 0,
      "rushing_yards": 0,
      "rushing_tds": 0,
      "receiving_yards": 0,
      "receiving_tds": 0,
      "fumble_tds": 0,
      "two_point_conversions": 0,
      "fumbles_lost": 0,
      "fantasy_points": 0.0,
      "lineup_status": "starter",
      "player_id": "2562502"
    }
  ],
  "source": "html_scraping"
}