{
  "players": [
    {
      "position": "QB",
      "name": "Drew Brees",
      "nfl_team": "NO",
      "game_result": "Win",
      "game_score": "16-14",
      "passing_yards": 322,
      "passing_tds": 1,
      "interceptions": 2,
      "rushing_yards": 0,
      "rushing_tds": 0,
      "receiving_yards": 0,
      "receiving_tds": 0,
      "fumble_tds": 0,
      "two_point_conversions": 0,
      "fumbles_lost": 0,
      "fantasy_points": 12.88,
      "touchdowns": 1,
      "lineup_status": "starter",
      "player_id": "2504775"
    },
    {
      "position": "RB",
      "name": "BenJarvus Green-Ellis",
      "nfl_team": "CIN",
      "game_result": "Win",
      "game_score": "20-10",
      "passing_yards": 0,
      "passing_tds": 0,
      "interceptions": 0,
      "rushing_yards": 75,
      "rushing_tds": 0,
      "receiving_yards": 5,
      "receiving_tds": 0,
      "fumble_tds": 0,
      "two_point_conversions": 0,
      "fumbles_lost": 0,
      "fantasy_points": 8.0,
      "lineup_status": "starter",
      "player_id": "929"
    },
    {
      "position": "RB",
      "name": "Trent Richardson",
      "nfl_team": "IND",
      "game_result": "Loss",
      "game_score": "20-24",
      "passing_yards": 0,
      "passing_tds": 0,
      "interceptions": 0,
      "rushing_yards": 58,
      "rushing_tds": 0,
      "receiving_yards": 21,
      "receiving_tds": 0,
      "fumble_tds": 0,
      "two_point_conversions": 0,
      "fumbles_lost": 0,
      "fantasy_points": 7.9,
      "lineup_status": "starter",
      "player_id": "2533032"
    },
    {
      "position": "WR",
      "name": "Jordy Nelson",
      "nfl_team": "GB",
      "game_result": "Win",
      "game_score": "38-20",
      "passing_yards": 0,
      "passing_tds": 0,
      "interceptions": 0,
      "rushing_yards": 0,
      "rushing_tds": 0,
      "receiving_yards": 66,
      "receiving_tds": 2,
      "fumble_tds": 0,
      "two_point_conversions": 0,
      "fumbles_lost": 0,
      "fantasy_points": 18.6,
      "touchdowns": 2,
      "lineup_status": "starter",
      "player_id": "1032"
    },
    {
      "position": "WR",
      "name": "Chris Givens",
      "nfl_team": "STL",
      "game_result": "Loss",
      "game_score": "24-31",
      "passing_yards": 0,
      "passing_tds": 0,
      "interceptions": 0,
      "rushing_yards": 0,
      "rushing_tds": 0,
      "receiving_yards": 105,
      "receiving_tds": 0,
      "fumble_tds": 0,
      "two_point_conversions": 0,
      "fumbles_lost": 0,
      "fantasy_points": 10.5,
      "lineup_status": "starter",
      "player_id": "2535634"
    },
    {
      "position": "TE",
      "name": "Jermichael Finley",
      "nfl_team": "GB",
      "game_result": "Win",
      "game_score": "38-20",
      "passing_yards": 0,
      "passing_tds": 0,
      "interceptions": 0,
      "rushing_yards": 0,
      "rushing_tds": 0,
      "receiving_yards": 65,
      "receiving_tds": 1,
      "fumble_tds": 0,
      "two_point_conversions": 0,
      "fumbles_lost": 0,
      "fantasy_points": 12.5,
      "touchdowns": 1,
      "lineup_status": "starter",
      "player_id": "1072"
    },
    {
      "position": "RB",
      "name": "Darren Sproles",
      "nfl_team": "NO",
      "game_result": "Win",
      "game_score": "16-14",
      "passing_yards": 0,
      "passing_tds": 0,
      "interceptions": 0,
      "rushing_yards": 26,
      "rushing_tds": 0,
      "receiving_yards": 36,
      "receiving_tds": 0,
      "fumble_tds": 0,
      "two_point_conversions": 0,
      "fumbles_lost": 0,
      "fantasy_points": 6.2,
      "lineup_status": "starter",
      "player_id": "2506467"
    },
    {
      "position": "TE",
      "name": "Rob Gronkowski",
      "nfl_team": "NE",
      "game_result": "Win",
      "game_score": "13-10",
      "passing_yards": 0,
      "passing_tds": 0,
      "interceptions": 0,
      "rushing_yards": 0,
      "rushing_tds": 0,
      "receiving_yards": 0,
      "receiving_tds": 0,
      "fumble_tds": 0,
      "two_point_conversions": 0,
      "fumbles_lost": 0,
      "fantasy_points": 0.0,
      "lineup_status": "starter",
      "player_id": "497240"
    },
    {
      "position": "RB",
      "name": "Kendall Hunter",
      "nfl_team": "SF",
      "game_result": "Loss",
      "game_score": "3-29",
      "passing_yards": 0,
      "passing_tds": 0,
      "interceptions": 0,
      "rushing_yards": -7,
      "rushing_tds": 0,
      "receiving_yards": 0,
      "receiving_tds": 0,
      "fumble_tds": 0,
      "two_point_conversions": 0,
      "fumbles_lost": 0,
      "fantasy_points": 0.7,
      "lineup_status": "starter",
      "player_id": "2495172"
    },
    {
      "position": "RB",
      "name": "Mikel Leshoure",
      "nfl_team": "DET",
      "game_result": "Loss",
      "game_score": "21-25",
      "passing_yards": 0,
      "passing_tds": 0,
      "interceptions": 0,
      "rushing_yards": 0,
      "rushing_tds": 0,
      "receiving_yards": 0,
      "receiving_tds": 0,
      "fumble_tds": 0,
      "two_point_conversions": 0,
      "fumbles_lost": 0,
      "fantasy_points": 0.0,
      "lineup_status": "starter",
      "player_id": "2495468"
    },
    {
      "position": "QB",
      "name": "Michael Vick",
      "nfl_team": "PHI",
      "game_result": "Loss",
      "game_score": "30-33",
      "passing_yards": 428,
      "passing_tds": 2,
      "interceptions": 0,
      "rushing_yards": 34,
      "rushing_tds": 1,
      "receiving_yards": -2,
      "receiving_tds": 0,
      "fumble_tds": 0,
      "two_point_conversions": 0,
      "fumbles_lost": 0,
      "fantasy_points": 34.32,
      "touchdowns": 3,
      "lineup_status": "starter",
      "player_id": "2504531"
    },
    {
      "position": "WR",
      "name": "Roddy White",
      "nfl_team": "ATL",
      "game_result": "Win",
      "game_score": "31-24",
      "passing_yards": 0,
      "passing_tds": 0,
      "interceptions": 0,
      "rushing_yards": 0,
      "rushing_tds": 0,
      "receiving_yards": 21,
      "receiving_tds": 0,
      "fumble_tds": 0,
      "two_point_conversions": 0,
      "fumbles_lost": 0,
      "fantasy_points": 2.1,
      "lineup_status": "starter",
      "player_id": "2506366"
    },
    {
      "position": "WR",
      "name": "T.Y. Hilton",
      "nfl_team": "IND",
      "game_result": "Loss",
      "game_score": "20-24",
      "passing_yards": 0,
      "passing_tds": 0,
      "interceptions": 0,
      "rushing_yards": 0,
      "rushing_tds": 0,
      "receiving_yards": 124,
      "receiving_tds": 0,
      "fumble_tds": 0,
      "two_point_conversions": 0,
      "fumbles_lost": 0,
      "fantasy_points": 12.4,
      "lineup_status": "starter",
      "player_id": "2532865"
    }
  ],
  "source": "html_scraping"
}