{
  "games": [
    {
      "away_points": 107.42,
      "away_rank": 10,
      "away_record": "1-4-0",
      "away_team": "No League for Old Men",
      "away_team_id": "12",
      "game_id": "201805112",
      "home_points": 110.78,
      "home_rank": 8,
      "home_record": "2-3-0",
      "home_team": "Johnson and Johnson",
      "home_team_id": "1",
      "scraped_at": "2025-06-30T22:46:13.215Z",
      "season": 2018,
      "week": 5
    },
    {
      "away_points": 119.12,
      "away_rank": 3,
      "away_record": "4-1-0",
      "away_team": "BreesCassidyandtheStefonDiggs",
      "away_team_id": "11",
      "game_id": "201805311",
      "home_points": 62.82,
      "home_rank": 11,
      "home_record": "1-4-0",
      "home_team": "Capn' Geno's",
      "home_team_id": "3",
      "scraped_at": "2025-06-30T22:46:13.215Z",
      "season": 2018,
      "week": 5
    },
    {
      "away_points": 112.5,
      "away_rank": 7,
      "away_record": "2-3-0",
      "away_team": "Watson on Sunshine",
      "away_team_id": "4",
      "game_id": "20180564",
      "home_points": 115.94,
      "home_rank": 5,
      "home_record": "3-2-0",
      "home_team": "Roaring Rivers of Freedom",
      "home_team_id": "6",
      "scraped_at": "2025-06-30T22:46:13.215Z",
      "season": 2018,
      "week": 5
    },
    {
      "away_points": 56.94,
      "away_rank": 4,
      "away_record": "4-1-0",
      "away_team": "Mahomes Room",
      "away_team_id": "9",
      "game_id": "201805109",
      "home_points": 107.04,
      "home_rank": 2,
      "home_record": "4-1-0",
      "home_team": "Risk It For The Trubiscuit",
      "home_team_id": "10",
      "scraped_at": "2025-06-30T22:46:13.215Z",
      "season": 2018,
      "week": 5
    },
    {
      "away_points": 95.5,
      "away_rank": 12,
      "away_record": "1-4-0",
      "away_team": "Pop Lockett Drop It",
      "away_team_id": "8",
      "game_id": "20180528",
      "home_points": 66.7,
      "home_rank": 6,
      "home_record": "2-3-0",
      "home_team": "ZekeZone",
      "home_team_id": "2",
      "scraped_at": "2025-06-30T22:46:13.215Z",
      "season": 2018,
      "week": 5
    },
    {
      "away_points": 119.44,
      "away_rank": 9,
      "away_record": "2-3-0",
      "away_team": "The Great Gronksby",
      "away_team_id": "7",
      "game_id": "20180557",
      "home_points": 97.68,
      "home_rank": 1,
      "home_record": "4-1-0",
      "home_team": "Kamara Obscura",
      "home_team_id": "5",
      "scraped_at": "2025-06-30T22:46:13.215Z",
      "season": 2018,
      "week": 5
    }
  ]
}